setup.py
django_upyun/__init__.py
django_upyun/models.py
django_upyun/storage.py
django_upyun/tests.py
django_upyun_storage.egg-info/PKG-INFO
django_upyun_storage.egg-info/SOURCES.txt
django_upyun_storage.egg-info/dependency_links.txt
django_upyun_storage.egg-info/requires.txt
django_upyun_storage.egg-info/top_level.txt