Metadata-Version: 1.0
Name: django-upyun-storage
Version: 0.0.1
Summary: django storage for upyun.com
Home-page: https://github.com/waylybaye/django-upyun
Author: Baye Wayly
Author-email: baye@wayly.net
License: MIT
Platform: UNKNOWN
Classifier: Development Status :: 2 - Pre-Alpha
Classifier: Environment :: Web Environment
Classifier: Framework :: Django
Classifier: Intended Audience :: Developers
Classifier: Operating System :: OS Independent
Classifier: Programming Language :: Python
Classifier: Topic :: Utilities
